brownllama/__init__.py
brownllama/bigquery.py
brownllama/bq_query.py
brownllama/bright_sky.py
brownllama/case_converter.py
brownllama/gemini.py
brownllama/langdock.py
brownllama/logger.py
brownllama/secret_manager.py
brownllama/storage.py
brownllama-0.1.37.dist-info/METADATA
brownllama-0.1.37.dist-info/WHEEL
brownllama-0.1.37.dist-info/licenses/LICENSE
brownllama-0.1.37.dist-info/RECORD
