Metadata-Version: 2.4
Name: brownllama
Version: 0.1.37
Summary: Standard PIP Package for GCP integration apps.
Author-email: Sanu Maharjan <inbox.sanu@gmail.com>
License-File: LICENSE
Classifier: Programming Language :: Python :: 3 :: Only
Classifier: Programming Language :: Python :: 3.12
Classifier: Programming Language :: Python :: 3.13
Requires-Python: >=3.12
Requires-Dist: build>=1.2.2.post1
Requires-Dist: google-cloud-bigquery>=3.34
Requires-Dist: google-cloud-secret-manager>=2.23.3
Requires-Dist: google-cloud-storage>=3.1
Requires-Dist: google-genai>=1.30
Requires-Dist: pandas>=2.2.3
Requires-Dist: pydantic>=2.11.5
Requires-Dist: requests>=2.32.3
Requires-Dist: twine>=6.1
